.coveragerc
LICENSE
MANIFEST.in
README.md
dev_requirements.txt
requirements.txt
setup.cfg
setup.py
versioneer.py
csirtg_peers/__init__.py
csirtg_peers/_version.py
csirtg_peers.egg-info/PKG-INFO
csirtg_peers.egg-info/SOURCES.txt
csirtg_peers.egg-info/dependency_links.txt
csirtg_peers.egg-info/entry_points.txt
csirtg_peers.egg-info/requires.txt
csirtg_peers.egg-info/top_level.txt
test/test_basics.py