Metadata-Version: 1.1
Name: csirtg-peers
Version: 0.3
Summary: CSIRTG Peers Utility
Home-page: https://github.com/csirtgadgets/csirtg-peers
Author: Wes Young
Author-email: wes@csirtgadgets.com
License: MPL2
Keywords: security
Platform: UNKNOWN
Classifier: Programming Language :: Python
